{"version": "1", "message": "ERROR: Hidden Testcases server unreachable.", "problem_id": "ads2_m12_a1_1", "user_id": "VINODKUMARREDDYM", "score": {"sample": {"0": {"execution_time": 0.07889223098754883, "passed": false}, "1": {"execution_time": 0.0833580493927002, "passed": false}, "2": {"execution_time": 0.07820916175842285, "passed": false}, "3": {"execution_time": 0.0784757137298584, "passed": false}, "4": {"execution_time": 0.07781767845153809, "passed": false}, "5": {"execution_time": 0.07754683494567871, "passed": false}}}, "check_style_score": "0/1"}