{"version": "1", "message": "ERROR: Hidden Testcases server unreachable.", "problem_id": "ads2_m12_a1_1", "user_id": "VINODKUMARREDDYM", "score": {"sample": {"0": {"execution_time": 0.07957959175109863, "passed": false}, "1": {"execution_time": 0.07789111137390137, "passed": false}, "2": {"execution_time": 0.2363748550415039, "passed": false}, "3": {"execution_time": 0.07821798324584961, "passed": false}, "4": {"execution_time": 0.07926130294799805, "passed": false}, "5": {"execution_time": 0.07954120635986328, "passed": false}}}, "check_style_score": "0/1"}